{
	"textures": [
		{
			"image": "chort",
			"format": "RGBA8888",
			"size": {
				"w": 64,
				"h": 25
			},
			"scale": 1,
			"frames": [
				{
					"filename": "chort_run_anim_f1",
					"rotated": false,
					"trimmed": true,
					"sourceSize": {
						"w": 16,
						"h": 24
					},
					"spriteSourceSize": {
						"x": 0,
						"y": 0,
						"w": 16,
						"h": 23
					},
					"frame": {
						"x": 1,
						"y": 1,
						"w": 16,
						"h": 23
					}
				},
				{
					"filename": "chort_run_anim_f0",
					"rotated": false,
					"trimmed": true,
					"sourceSize": {
						"w": 16,
						"h": 24
					},
					"spriteSourceSize": {
						"x": 2,
						"y": 2,
						"w": 13,
						"h": 22
					},
					"frame": {
						"x": 19,
						"y": 1,
						"w": 13,
						"h": 22
					}
				},
				{
					"filename": "chort_run_anim_f2",
					"rotated": false,
					"trimmed": true,
					"sourceSize": {
						"w": 16,
						"h": 24
					},
					"spriteSourceSize": {
						"x": 1,
						"y": 4,
						"w": 14,
						"h": 20
					},
					"frame": {
						"x": 34,
						"y": 1,
						"w": 14,
						"h": 20
					}
				},
				{
					"filename": "chort_run_anim_f3",
					"rotated": false,
					"trimmed": true,
					"sourceSize": {
						"w": 16,
						"h": 24
					},
					"spriteSourceSize": {
						"x": 2,
						"y": 7,
						"w": 13,
						"h": 17
					},
					"frame": {
						"x": 50,
						"y": 1,
						"w": 13,
						"h": 17
					}
				}
			]
		}
	],
	"meta": {
		"app": "https://www.codeandweb.com/texturepacker",
		"version": "3.0",
		"smartupdate": "$TexturePacker:SmartUpdate:78f6ec150ecd73483c7ce11b95dc4aa1:655656bb911ff93c790684b43a30a6f0:7895e5084034ba038152309a9066ba35$"
	}
}
